Workbook
Name SponsoredProductsEntityNames: [1]Config!$B$2:$J$2
Name SponsoredProductsOperationNames: [1]Config!$B$3:$D$3

Sheet 广告组合预算
B1: 合计 | I1: =SUM(I4:I48) | J1: =SUM(J4:J48) | K1: =J1/I1 | L1: =SUM(L4:L48) | M1: =L1/J1 | N1: =SUM(N4:N48) | O1: =SUM(O4:O48) | P1: =L1/O1 | Q1: =1/P1 | R1: =SUM(R4:R48) | S1: =SUM(S4:S48) | T1: =SUM(T4:T48) | U1: =SUM(U4:U48) | V1: =SUM(V4:V48) | W1: =SUM(W4:W48)
B2: 筛选求和 | I2: =SUBTOTAL(9,I4:I44) | J2: =SUBTOTAL(9,J4:J44) | K2: =J2/I2 | L2: =SUBTOTAL(9,L4:L44) | M2: =L2/J2 | N2: =SUBTOTAL(9,N4:N44) | O2: =SUBTOTAL(9,O4:O44) | P2: =L2/O2 | Q2: =1/P2 | R2: =SUBTOTAL(9,R4:R44) | S2: =SUBTOTAL(9,S4:S44) | T2: =SUBTOTAL(9,T4:T44) | U2: =SUBTOTAL(9,U4:U44) | V2: =SUBTOTAL(9,V4:V44) | W2: =SUBTOTAL(9,W4:W44) | AF2: 需要控制多少预算
A3: 状态 | B3: 广告组合 | C3: 状态 | D3: 预算类型 | E3: 预算(USD) | F3: 预算开始日期 | G3: 预算结束日期 | H3: 广告活动数量 | I3: 展示次数 | J3: 点击量 | K3: CTR | L3: 支出(USD) | M3: CPC(USD) | N3: 订单数量 | O3: 销量(USD) | P3: ACOS | Q3: 广告投资回报率 (ROAS) | R3: NTB 订单数量 | S3: NTB 订单数量百分比 | T3: NTB 销售额(USD) | U3: 品牌新客销售额比例 | V3: 可见展示量 | W3: VCPM(USD) | X3: CVR | Y3: AVP | Z3: 销售占比 | AA3: 花费占比 | AB3: 差值 | AC3: 日花费 | AD3: 组合月预算 | AE3: 客单价 | AF3: 0.8
B20: 天数 | C20: 30
B21: 日花费 | C21: =IFERROR(L2/C20,0)
V27: =24-10

Sheet Bulk
AF1: Exact | AR1: =SUMIF(AF$14:AF$199994,AF1,AR$14:AR$1000006) | AS1: =SUMIF(AF$14:AF$199994,AF1,AS$14:AS$1000004) | AU1: =SUMIF(AF$14:AF$199994,AF1,AU$14:AU$200004) | AV1: =SUMIF(AF$14:AF$199994,AF1,AV$14:AV$200004) | AW1: =SUMIF(AF$14:AF$199994,AF1,AW$14:AW$200004)
AF2: Phrase | AR2: =SUMIF(AF$14:AF$199994,AF2,AR$14:AR$1000006) | AS2: =SUMIF(AF$14:AF$199994,AF2,AS$14:AS$1000004) | AU2: =SUMIF(AF$14:AF$199994,AF2,AU$14:AU$200004) | AV2: =SUMIF(AF$14:AF$199994,AF2,AV$14:AV$200004) | AW2: =SUMIF(AF$14:AF$199994,AF2,AW$14:AW$200004)
AF3: Broad | AR3: =SUMIF(AF$14:AF$199994,AF3,AR$14:AR$1000006) | AS3: =SUMIF(AF$14:AF$199994,AF3,AS$14:AS$1000004) | AU3: =SUMIF(AF$14:AF$199994,AF3,AU$14:AU$200004) | AV3: =SUMIF(AF$14:AF$199994,AF3,AV$14:AV$200004) | AW3: =SUMIF(AF$14:AF$199994,AF3,AW$14:AW$200004)
AF4: Product Targeting | AR4: =SUMIF(B$15:B$199994,AF4,AR$15:AR$200004) | AS4: =SUMIF(B$15:B$199993,AF4,AS$15:AS$200004) | AU4: =SUMIF(B$15:B$199993,AF4,AU$15:AU$200004) | AV4: =SUMIF(B$15:B$199993,AF4,AV$15:AV$200004) | AW4: =SUMIF(B$15:B$199993,AF4,AW$15:AW$200004)
AF5: asin= | AR5: {=SUM(IF(ISNUMBER(SEARCH($AF$5,$AJ$15:$AJ$100000)),$AR$15:$AR$100000,0))} | AS5: {=SUM(IF(ISNUMBER(SEARCH($AF$5,$AJ$15:$AJ$100000)),$AS$15:$AS$100000,0))} | AU5: {=SUM(IF(ISNUMBER(SEARCH($AF$5,$AJ$15:$AJ$100000)),$AU$15:$AU$100000,0))} | AV5: {=SUM(IF(ISNUMBER(SEARCH($AF$5,$AJ$15:$AJ$100000)),$AV$15:$AV$100000,0))} | AW5: {=SUM(IF(ISNUMBER(SEARCH($AF$5,$AJ$15:$AJ$100000)),$AW$15:$AW$100000,0))}
AF6: asin-expanded= | AR6: {=SUM(IF(ISNUMBER(SEARCH(AF6,$AJ$15:$AJ$100000)),$AR$15:$AR$100000,0))} | AS6: {=SUM(IF(ISNUMBER(SEARCH($AF$6,$AJ$15:$AJ$100000)),$AS$15:$AS$100000,0))} | AU6: {=SUM(IF(ISNUMBER(SEARCH($AF$6,$AJ$15:$AJ$100000)),$AU$15:$AU$100000,0))} | AV6: {=SUM(IF(ISNUMBER(SEARCH($AF$6,$AJ$15:$AJ$100000)),$AV$15:$AV$100000,0))} | AW6: {=SUM(IF(ISNUMBER(SEARCH($AF$6,$AJ$15:$AJ$100000)),$AW$15:$AW$100000,0))}
AF7: category= | AR7: {=SUM(IF(ISNUMBER(SEARCH(AF7,$AJ$15:$AJ$100000)),$AR$15:$AR$100000,0))} | AS7: {=SUM(IF(ISNUMBER(SEARCH($AF$7,$AJ$15:$AJ$100000)),$AS$15:$AS$100000,0))} | AU7: {=SUM(IF(ISNUMBER(SEARCH($AF$7,$AJ$15:$AJ$100000)),$AU$15:$AU$100000,0))} | AV7: {=SUM(IF(ISNUMBER(SEARCH($AF$7,$AJ$15:$AJ$100000)),$AV$15:$AV$100000,0))} | AW7: {=SUM(IF(ISNUMBER(SEARCH($AF$7,$AJ$15:$AJ$100000)),$AW$15:$AW$100000,0))}
AF8: complements | AR8: =SUMIF(AJ$14:AJ$199994,AF8,AR$14:AR$200004) | AS8: =SUMIF(AJ$14:AJ$199993,AF8,AS$14:AS$200004) | AU8: =SUMIF(AJ$15:AJ$199996,AF8,AU$15:AU$200004) | AV8: =SUMIF(AJ$15:AJ$199996,AF8,AV$15:AV$200005) | AW8: =SUMIF(AJ$15:AJ$199995,AF8,AW$15:AW$200004)
AF9: loose-match | AR9: =SUMIF(AJ$14:AJ$199994,AF9,AR$14:AR$200004) | AS9: =SUMIF(AJ$14:AJ$199993,AF9,AS$14:AS$200004) | AU9: =SUMIF(AJ$15:AJ$199993,AF9,AU$15:AU$200004) | AV9: =SUMIF(AJ$15:AJ$199993,AF9,AV$15:AV$200004) | AW9: =SUMIF(AJ$15:AJ$199993,AF9,AW$15:AW$200004)
AF10: close-match | AR10: =SUMIF(AJ$14:AJ$199994,AF10,AR$14:AR$200004) | AS10: =SUMIF(AJ$14:AJ$199993,AF10,AS$14:AS$200004) | AU10: =SUMIF(AJ$15:AJ$199996,AF10,AU$15:AU$200005) | AV10: =SUMIF(AJ$15:AJ$199993,AF10,AV$15:AV$200004) | AW10: =SUMIF(AJ$15:AJ$199993,AF10,AW$15:AW$200004)
AF11: substitutes | AR11: =SUMIF(AJ$14:AJ$199994,AF11,AR$14:AR$200004) | AS11: =SUMIF(AJ$14:AJ$199993,AF11,AS$14:AS$200004) | AU11: =SUMIF(AJ$15:AJ$199993,AF11,AU$15:AU$200004) | AV11: =SUMIF(AJ$15:AJ$199993,AF11,AV$15:AV$200004) | AW11: =SUMIF(AJ$15:AJ$199993,AF11,AW$15:AW$200004)
AF12: 合计 | AR12: =SUM(AR15:AR100006) | AS12: =SUM(AS15:AS100006) | AT12: =AS12/AR12 | AU12: =SUM(AU15:AU100006) | AV12: =SUM(AV15:AV100006) | AW12: =SUM(AW15:AW100006) | AY12: =AW12/AS12 | AZ12: =AU12/AV12 | BA12: =AU12/AS12
AF13: 筛选求和 | AR13: =SUBTOTAL(9,AR15:AR26618) | AS13: =SUBTOTAL(9,AS15:AS26618) | AT13: =AS13/AR13 | AU13: =SUBTOTAL(9,AU15:AU26618) | AV13: =SUBTOTAL(9,AV15:AV26618) | AW13: =SUBTOTAL(9,AW15:AW26618) | AY13: =AW13/AS13 | AZ13: =AU13/AV13 | BA13: =AU13/AS13 | BC13: =AU13/AU12 | BD13: =AV13/AV12 | BE13: =BD13-BC13
A14: Product | B14: Entity | C14: Operation | D14: Campaign ID | E14: Ad Group ID | F14: Portfolio ID | G14: Ad ID | H14: Keyword ID | I14: Product Targeting ID | J14: Campaign Name | K14: Ad Group Name | L14: Campaign Name (Informational only) | M14: Ad Group Name (Informational only) | N14: Portfolio Name (Informational only) | O14: Start Date | P14: End Date | Q14: Targeting Type | R14: State | S14: Campaign State (Informational only) | T14: Ad Group State (Informational only) | U14: Daily Budget | V14: SKU | W14: ASIN (Informational only) | X14: Eligibility Status (Informational only) | Y14: Reason for Ineligibility (Informational only) | Z14: Ad Group Default Bid | AA14: Ad Group Default Bid (Informational only) | AB14: Bid | AC14: Keyword Text | AD14: Native Language Keyword | AE14: Native Language Locale | AF14: Match Type | AG14: Bidding Strategy | AH14: Placement | AI14: Percentage | AJ14: Product Targeting Expression | AK14: Resolved Product Targeting Expression (Informational only) | AL14: Audience ID | AM14: Shopper Cohort Percentage | AN14: Shopper Cohort Type | AO14: Segment Name (Informational only) | AP14: Sites | AQ14: Off-Amazon ad serving | AR14: Impressions | AS14: Clicks | AT14: Click-through Rate | AU14: Spend | AV14: Sales | AW14: Orders | AX14: Units | AY14: Conversion Rate | AZ14: ACOS | BA14: CPC | BB14: ROAS

Sheet BidingAdjustment
AH1: Placement Product Page | AR1: =SUMIF(AH$6:AH$199986,AH1,AR$6:AR$199996) | AS1: =SUMIF(AH$6:AH$199986,AH1,AS$6:AS$199996) | AU1: =SUMIF(AH$6:AH$199986,AH1,AU$6:AU$199996) | AV1: =SUMIF(AH$6:AH$199986,AH1,AV$6:AV$199996) | AW1: =SUMIF(AH$6:AH$199986,AH1,AW$6:AW$199996)
AH2: Placement Rest Of Search | AR2: =SUMIF(AH$6:AH$199986,AH2,AR$6:AR$199996) | AS2: =SUMIF(AH$6:AH$199986,AH2,AS$6:AS$199996) | AU2: =SUMIF(AH$6:AH$199986,AH2,AU$6:AU$199996) | AV2: =SUMIF(AH$6:AH$199986,AH2,AV$6:AV$199996) | AW2: =SUMIF(AH$6:AH$199986,AH2,AW$6:AW$199996)
AH3: Placement Top | AR3: =SUMIF(AH$6:AH$199986,AH3,AR$6:AR$199996) | AS3: =SUMIF(AH$6:AH$199986,AH3,AS$6:AS$199996) | AU3: =SUMIF(AH$6:AH$199986,AH3,AU$6:AU$199996) | AV3: =SUMIF(AH$6:AH$199986,AH3,AV$6:AV$199996) | AW3: =SUMIF(AH$6:AH$199986,AH3,AW$6:AW$199996)
AH4: Placement Amazon Business | AR4: =SUMIF(AH$6:AH$199986,AH4,AR$6:AR$199996) | AS4: =SUMIF(AH$6:AH$199986,AH4,AS$6:AS$199996) | AU4: =SUMIF(AH$6:AH$199986,AH4,AU$6:AU$199996) | AV4: =SUMIF(AH$6:AH$199986,AH4,AV$6:AV$199996) | AW4: =SUMIF(AH$6:AH$199986,AH4,AW$6:AW$199996)
A5: Product | B5: Entity | C5: Operation | D5: Campaign ID | E5: Ad Group ID | F5: Portfolio ID | G5: Ad ID | H5: Keyword ID | I5: Product Targeting ID | J5: Campaign Name | K5: Ad Group Name | L5: Campaign Name (Informational only) | M5: Ad Group Name (Informational only) | N5: Portfolio Name (Informational only) | O5: Start Date | P5: End Date | Q5: Targeting Type | R5: State | S5: Campaign State (Informational only) | T5: Ad Group State (Informational only) | U5: Daily Budget | V5: SKU | W5: ASIN (Informational only) | X5: Eligibility Status (Informational only) | Y5: Reason for Ineligibility (Informational only) | Z5: Ad Group Default Bid | AA5: Ad Group Default Bid (Informational only) | AB5: Bid | AC5: Keyword Text | AD5: Native Language Keyword | AE5: Native Language Locale | AF5: Match Type | AG5: Bidding Strategy | AH5: Placement | AI5: Percentage | AJ5: Product Targeting Expression | AK5: Resolved Product Targeting Expression (Informational only) | AL5: Audience ID | AM5: Shopper Cohort Percentage | AN5: Shopper Cohort Type | AO5: Segment Name (Informational only) | AP5: Sites | AQ5: Off-Amazon ad serving | AR5: Impressions | AS5: Clicks | AT5: Click-through Rate | AU5: Spend | AV5: Sales | AW5: Orders | AX5: Units | AY5: Conversion Rate | AZ5: ACOS | BA5: CPC | BB5: ROAS

Sheet 广告位可视化
B1: Placement | C1: 求和项:Impressions | D1: 求和项:Clicks | E1: 求和项:Spend | F1: 求和项:Sales | G1: 求和项:Orders | H1: CPC | I1: CTR | J1: CVR | K1: ACoS | L1: CPM | M1: CPO | N1: 客单价 | O1: 销售占比 | P1: 花费占比 | Q1: 差值 | R1: ACoS | S1: RoAS | U1: 场景/活动目的 | V1: ß | W1: 0.2
B2: Placement Product Page | C2: =BidingAdjustment!AR1 | D2: =BidingAdjustment!AS1 | E2: =BidingAdjustment!AU1 | F2: =BidingAdjustment!AV1 | G2: =BidingAdjustment!AW1 | H2: =E2/D2 | I2: =IFERROR(D2/C2,0) | J2: =IFERROR(G2/D2,0) | K2: =IFERROR(E2/F2,0) | L2: =E2/C2*1000 | M2: =IFERROR(E2/G2,"") | N2: =IFERROR(F2/G2,"") | O2: =F2/$F$6 | P2: =E2/$E$6 | Q2: =O2-P2 | R2: =K2 | S2: =1/K2 | U2: 当投放订单=0 | V2: 降费Ctr | W2: =$I$6*0.8
B3: Placement Rest Of Search | C3: =BidingAdjustment!AR2 | D3: =BidingAdjustment!AS2 | E3: =BidingAdjustment!AU2 | F3: =BidingAdjustment!AV2 | G3: =BidingAdjustment!AW2 | H3: =E3/D3 | I3: =IFERROR(D3/C3,0) | J3: =IFERROR(G3/D3,0) | K3: =IFERROR(E3/F3,0) | L3: =E3/C3*1000 | M3: =IFERROR(E3/G3,"") | N3: =IFERROR(F3/G3,"") | O3: =F3/$F$6 | P3: =E3/$E$6 | Q3: =O3-P3 | R3: =K3 | S3: =1/K3 | V3: 增投Ctr | W3: =$I$6*1.2
B4: Placement Top | C4: =BidingAdjustment!AR3 | D4: =BidingAdjustment!AS3 | E4: =BidingAdjustment!AU3 | F4: =BidingAdjustment!AV3 | G4: =BidingAdjustment!AW3 | H4: =E4/D4 | I4: =IFERROR(D4/C4,0) | J4: =IFERROR(G4/D4,0) | K4: =IFERROR(E4/F4,0) | L4: =E4/C4*1000 | M4: =IFERROR(E4/G4,"") | N4: =IFERROR(F4/G4,"") | O4: =F4/$F$6 | P4: =E4/$E$6 | Q4: =O4-P4 | R4: =K4 | S4: =1/K4 | U4: 自然位 | V4: 降费Cvr | W4: =$J$6*0.8
B5: Placement Amazon Business | C5: =BidingAdjustment!AR4 | D5: =BidingAdjustment!AS4 | E5: =BidingAdjustment!AU4 | F5: =BidingAdjustment!AV4 | G5: =BidingAdjustment!AW4 | H5: =E5/D5 | I5: =IFERROR(D5/C5,0) | J5: =IFERROR(G5/D5,0) | K5: =IFERROR(E5/F5,0) | L5: =E5/C5*1000 | M5: =IFERROR(E5/G5,"") | N5: =IFERROR(F5/G5,"") | O5: =F5/$F$6 | P5: =E5/$E$6 | Q5: =O5-P5 | R5: =K5 | S5: =1/K5 | V5: 增投Cvr | W5: =$J$6*1.2
B6: 总计 | C6: =SUM(C2:C5) | D6: =SUM(D2:D5) | E6: =SUM(E2:E5) | F6: =SUM(F2:F5) | G6: =SUM(G2:G5) | H6: =E6/D6 | I6: =IFERROR(D6/C6,0) | J6: =IFERROR(G6/D6,0) | K6: =IFERROR(E6/F6,0) | L6: =E6/C6*1000 | M6: =IFERROR(E6/G6,"") | N6: =IFERROR(F6/G6,"") | O6: =F6/$F$6 | P6: =E6/$E$6 | Q6: =O6-P6 | R6: =K6 | S6: =1/K6 | U6: 广告单盈利 | V6: 降费ACoS | W6: =$K$6*1.2
V7: 增投ACoS | W7: =$K$6*0.8
B8: Bulk | C8: 求和项:Impressions | D8: 求和项:Clicks | E8: 求和项:Spend | F8: 求和项:Sales | G8: 求和项:Orders | H8: CPC | I8: CTR | J8: CVR | K8: ACoS | L8: CPM | M8: CPO | N8: 客单价 | O8: 销售占比 | P8: 花费占比 | Q8: 差值 | R8: ACoS | S8: RoAS
B9: Exact | C9: =Bulk!AR1 | D9: =Bulk!AS1 | E9: =Bulk!AU1 | F9: =Bulk!AV1 | G9: =Bulk!AW1 | H9: =E9/D9 | I9: =IFERROR(D9/C9,0) | J9: =IFERROR(G9/D9,0) | K9: =IFERROR(E9/F9,0) | L9: =E9/C9*1000 | M9: =IFERROR(E9/G9,"") | N9: =IFERROR(F9/G9,"") | O9: =F9/$F$20 | P9: =E9/$E$20 | Q9: =O9-P9 | R9: =K9 | S9: =1/K9 | U9: 报表周期 | V9: 20
B10: Phrase | C10: =Bulk!AR2 | D10: =Bulk!AS2 | E10: =Bulk!AU2 | F10: =Bulk!AV2 | G10: =Bulk!AW2 | H10: =E10/D10 | I10: =IFERROR(D10/C10,0) | J10: =IFERROR(G10/D10,0) | K10: =IFERROR(E10/F10,0) | L10: =E10/C10*1000 | M10: =IFERROR(E10/G10,"") | N10: =IFERROR(F10/G10,"") | O10: =F10/$F$20 | P10: =E10/$E$20 | Q10: =O10-P10 | R10: =K10 | S10: =1/K10 | U10: 日均标准 | V10: 2
B11: Broad | C11: =Bulk!AR3 | D11: =Bulk!AS3 | E11: =Bulk!AU3 | F11: =Bulk!AV3 | G11: =Bulk!AW3 | H11: =E11/D11 | I11: =IFERROR(D11/C11,0) | J11: =IFERROR(G11/D11,0) | K11: =IFERROR(E11/F11,0) | L11: =E11/C11*1000 | M11: =IFERROR(E11/G11,"") | N11: =IFERROR(F11/G11,"") | O11: =F11/$F$20 | P11: =E11/$E$20 | Q11: =O11-P11 | R11: =K11 | S11: =1/K11 | U11: Per订单标准 | V11: =V10*V9
B12: asin= | C12: =Bulk!AR5 | D12: =Bulk!AS5 | E12: =Bulk!AU5 | F12: =Bulk!AV5 | G12: =Bulk!AW5 | H12: =E12/D12 | I12: =IFERROR(D12/C12,0) | J12: =IFERROR(G12/D12,0) | K12: =IFERROR(E12/F12,0) | L12: =E12/C12*1000 | M12: =IFERROR(E12/G12,"") | N12: =IFERROR(F12/G12,"") | O12: =F12/$F$20 | P12: =E12/$E$20 | Q12: =O12-P12 | R12: =K12 | S12: =1/K12
B13: asin-expanded= | C13: =Bulk!AR6 | D13: =Bulk!AS6 | E13: =Bulk!AU6 | F13: =Bulk!AV6 | G13: =Bulk!AW6 | H13: =E13/D13 | I13: =IFERROR(D13/C13,0) | J13: =IFERROR(G13/D13,0) | K13: =IFERROR(E13/F13,0) | L13: =E13/C13*1000 | M13: =IFERROR(E13/G13,"") | N13: =IFERROR(F13/G13,"") | O13: =F13/$F$20 | P13: =E13/$E$20 | Q13: =O13-P13 | R13: =K13 | S13: =1/K13
B14: category= | C14: =Bulk!AR7 | D14: =Bulk!AS7 | E14: =Bulk!AU7 | F14: =Bulk!AV7 | G14: =Bulk!AW7 | H14: =E14/D14 | I14: =IFERROR(D14/C14,0) | J14: =IFERROR(G14/D14,0) | K14: =IFERROR(E14/F14,0) | L14: =E14/C14*1000 | M14: =IFERROR(E14/G14,"") | N14: =IFERROR(F14/G14,"") | O14: =F14/$F$20 | P14: =E14/$E$20 | Q14: =O14-P14 | R14: =K14 | S14: =1/K14
B15: complements | C15: =Bulk!AR8 | D15: =Bulk!AS8 | E15: =Bulk!AU8 | F15: =Bulk!AV8 | G15: =Bulk!AW8 | H15: =E15/D15 | I15: =IFERROR(D15/C15,0) | J15: =IFERROR(G15/D15,0) | K15: =IFERROR(E15/F15,0) | L15: =E15/C15*1000 | M15: =IFERROR(E15/G15,"") | N15: =IFERROR(F15/G15,"") | O15: =F15/$F$20 | P15: =E15/$E$20 | Q15: =O15-P15 | R15: =K15 | S15: =1/K15
B16: loose-match | C16: =Bulk!AR9 | D16: =Bulk!AS9 | E16: =Bulk!AU9 | F16: =Bulk!AV9 | G16: =Bulk!AW9 | H16: =E16/D16 | I16: =IFERROR(D16/C16,0) | J16: =IFERROR(G16/D16,0) | K16: =IFERROR(E16/F16,0) | L16: =E16/C16*1000 | M16: =IFERROR(E16/G16,"") | N16: =IFERROR(F16/G16,"") | O16: =F16/$F$20 | P16: =E16/$E$20 | Q16: =O16-P16 | R16: =K16 | S16: =1/K16
B17: close-match | C17: =Bulk!AR10 | D17: =Bulk!AS10 | E17: =Bulk!AU10 | F17: =Bulk!AV10 | G17: =Bulk!AW10 | H17: =E17/D17 | I17: =IFERROR(D17/C17,0) | J17: =IFERROR(G17/D17,0) | K17: =IFERROR(E17/F17,0) | L17: =E17/C17*1000 | M17: =IFERROR(E17/G17,"") | N17: =IFERROR(F17/G17,"") | O17: =F17/$F$20 | P17: =E17/$E$20 | Q17: =O17-P17 | R17: =K17 | S17: =1/K17
B18: substitutes | C18: =Bulk!AR11 | D18: =Bulk!AS11 | E18: =Bulk!AU11 | F18: =Bulk!AV11 | G18: =Bulk!AW11 | H18: =E18/D18 | I18: =IFERROR(D18/C18,0) | J18: =IFERROR(G18/D18,0) | K18: =IFERROR(E18/F18,0) | L18: =E18/C18*1000 | M18: =IFERROR(E18/G18,"") | N18: =IFERROR(F18/G18,"") | O18: =F18/$F$20 | P18: =E18/$E$20 | Q18: =O18-P18 | R18: =K18 | S18: =1/K18
B19: Product Targeting | C19: =Bulk!AR4 | D19: =Bulk!AS4 | E19: =Bulk!AU4 | F19: =Bulk!AV4 | G19: =Bulk!AW4 | H19: =E19/D19 | I19: =IFERROR(D19/C19,0) | J19: =IFERROR(G19/D19,0) | K19: =IFERROR(E19/F19,0) | L19: =E19/C19*1000 | M19: =IFERROR(E19/G19,"") | N19: =IFERROR(F19/G19,"") | O19: =F19/$F$20 | P19: =E19/$E$20 | Q19: =O19-P19 | R19: =K19 | S19: =1/K19
B20: 总计 | C20: =SUM(C9:C18) | D20: =SUM(D9:D18) | E20: =SUM(E9:E18) | F20: =SUM(F9:F18) | G20: =SUM(G9:G18) | H20: =E20/D20 | I20: =IFERROR(D20/C20,0) | J20: =IFERROR(G20/D20,0) | K20: =IFERROR(E20/F20,0) | L20: =E20/C20*1000 | M20: =IFERROR(E20/G20,"") | N20: =IFERROR(F20/G20,"") | O20: =F20/$F$20 | P20: =E20/$E$20 | Q20: =O20-P20 | R20: =K20 | S20: =1/K20

Sheet 搜索词模板
A1: 总计 | B1: =SUM(B4:B4089) | C1: =SUM(C4:C4089) | D1: =SUM(D4:D4089) | E1: =SUM(E4:E4089) | F1: =SUM(F4:F4089) | G1: =D1/C1 | H1: =C1/B1 | I1: =F1/C1 | J1: =D1/E1 | L1: =IFERROR(D1/F1,"N/A") | M1: =E1/F1 | O1: =C2/C1 | P1: =E2/E1 | Q1: =C2/B2 | S1: =E1/F1 | T1: =D2/D1 | AA1: 阶段选择 | AB1: 投放系数 | AD1: 1.1 | AE1: 0.9 | AF1: 0.7 | AG1: TOS | AJ1: ROS | AM1: PP
A2: 筛选求和 | B2: =SUBTOTAL(9,B4:B4089) | C2: =SUBTOTAL(9,C4:C4089) | D2: =SUBTOTAL(9,D4:D4089) | E2: =SUBTOTAL(9,E4:E4089) | F2: =SUBTOTAL(9,F4:F4089) | G2: =D2/C2 | H2: =C2/B2 | I2: =F2/C2 | J2: =D2/E2 | K2: =D2/B2*1000 | L2: =IFERROR(D2/F2,"N/A") | M2: =E2/F2 | N2: =L2/L1 | O2: =F2/F1 | P2: =E2/E1 | Q2: =D2/D1 | R2: =P2-Q2 | S2: =E2/F2 | AC2: 0.5 | AD2: =G2*$AD$1 | AE2: =G2*$AE$1 | AF2: =G2*$AF$1 | AG2: 0 | AH2: 0.5 | AI2: 1 | AJ2: 0 | AK2: 0.5 | AL2: 1 | AM2: 0 | AN2: 0.5 | AO2: 1
A3: Customer Search Term | B3: 求和项:Impressions | C3: 求和项:Clicks | D3: 求和项:Spend | E3: 求和项:Sales | F3: 求和项:Orders | G3: CPC | H3: CTR | I3: CVR | J3: ACoS | K3: CPM | L3: CPO | M3: AP | N3: Type（ASIN判断有公式） | O3: 搜索词销量占比（3%） | P3: 搜索词销售额占比 | Q3: 搜索词花费占比 | R3: 差值 | S3: LX_ASIN | T3: luggex | X3: ABA | Y3: 流量相关性（Cvr）判断 | Z3: ASIN竞争力评分（Price/Rating） | AA3: 第一KPI | AB3: 第二KPI | AC3: 备注 | AD3: Exact | AE3: Phrase | AF3: broad | AG3: TOS | AH3: TOS | AI3: TOS | AJ3: ROS | AK3: ROS | AL3: ROS | AM3: PP | AN3: PP | AO3: PP

Sheet 词频分析(全部搜索词）
A1: 词根 | B1: 出现次数 | C1: 占比 | D1: 求和项:展示量 | E1: 求和项:点击量 | F1: 求和项:花费 | G1: 求和项:7天总销售额 | H1: 求和项:7天总订单数(#) | I1: CPC | J1: CTR | K1: CVR | L1: ACoS | M1: 词根属性

Sheet 词频分析 (不出单搜素词)
A1: 词根 | B1: 出现次数 | C1: 占比 | D1: 求和项:展示量 | E1: 求和项:点击量 | F1: 求和项:花费 | G1: 求和项:7天总销售额 | H1: 求和项:7天总订单数(#) | I1: CPC | J1: CTR | K1: CVR | L1: ACoS | M1: 词根属性

Sheet LX_Asin
A1: ASIN | B1: SKU

Sheet NicheWord
A1: 细分市场名称：未提供（需额外上传 ABA / Opportunity Explorer 数据） | M1: 细分市场总点击数量 | N1: N/A
A2: 细分市场详情 - “搜索词” 选项卡 | R2: 客单价
Q3: 0.6 | R3: 90
Q4: =O4*$P$2 | R4: =1/Q4 | S4: 0.7 | T4: =R4*S4 | U4: =T4/V4 | V4: 49
A5: 搜索词 | B5: 搜索量（过去 360 天） | C5: 搜索量增长（过去 90 天） | D5: 搜索量增长（过去 180 天） | E5: 点击份额（过去 360 天） | F5: 搜索转化率（过去 360 天） | G5: 点击率最高的商品1（标题） | H5: 点击率最高的商品1 (ASIN) | I5: 点击率最高的商品2（标题） | J5: 点击率最高的商品2 (ASIN) | K5: 点击率最高的商品3（标题） | L5: 点击率最高的商品3 (ASIN) | M5: Click | N5: Order | O5: Cvr | P5: Order% | Q5: 预估广告转化率 | R5: 获单个订单-点击 | S5: CPC | T5: SPEND | U5: ACOS | V5: ACoAS

Sheet NicheAsin
A1: 细分市场名称：未提供（需额外上传 ABA / Opportunity Explorer 数据） | N1: 细分市场总点击数量（90%） | O1: =SUM(F6:F999)
A2: 细分市场详情 - “商品” 选项卡 | N2: 细分市场总点击数量 | O2: =O1/0.9
A5: 商品名称 | B5: ASIN | C5: 品牌 | D5: 类别 | E5: 发布日期 | F5: 细分市场点击量（过去 360 天） | G5: 点击份额（过去 360 天内） | H5: 平均售价（过去 360 天内）(USD) | I5: 总评分 | J5: 客户评分平均值 | K5: 畅销商品榜平均排名 | L5: 卖家和供应商的平均数量（过去 360 天内）

Sheet 否词库
A1: LISITNG | B1: 否定类型 | C1: 否定原因 | D1: 否定文本 | E1: 否定类型

Sheet H1F广告架构
A1: 流量方向
